[
  {
    "id": "gRDFwfGHCY9MULN5QEFQYvW1ZfvrSLnjkws58MwkfUkY",
    "name": "BTC/USDC",
    "dex": "Raydium",
    "category": "Major",
    "token1_symbol": "BTC",
    "token2_symbol": "USDC",
    "token1_address": "9n4nbM75f5Ui33ZbPYXn59EwSgE8CGsHtAeTH5YFeJ9E",
    "token2_address": "EPjFWdd5AufqSSqeM2qN1xzybapC8G4wEGGkZwyTDt1v",
    "liquidity": 43342391.97035079,
    "volume_24h": 5742226.861029971,
    "apr": 8.96128054534667,
    "fee": 0.0025,
    "version": "v4",
    "apr_change_24h": -0.20734663702203804,
    "apr_change_7d": 0.42629285308449383,
    "apr_change_30d": 6.090668774105474,
    "tvl_change_24h": 1.438922333383446,
    "tvl_change_7d": -2.2848969241770867,
    "tvl_change_30d": -12.919423735352993,
    "prediction_score": 65.97418703023112,
    "created_at": "2024-12-18T00:50:00.035612",
    "updated_at": "2025-04-26 00:50:00"
  },
  {
    "id": "Yburp2zPK9n1eSWqNgcK9QZaGQ7Dy89pafVaBXSdfVf3",
    "name": "SOL/USDT",
    "dex": "Meteora",
    "category": "Major",
    "token1_symbol": "SOL",
    "token2_symbol": "USDT",
    "token1_address": "So11111111111111111111111111111111111111112",
    "token2_address": "Es9vMFrzaCERmJfrF4H2FYD4KCoNkY11McCe8BenwNYB",
    "liquidity": 22618042.24871371,
    "volume_24h": 2232386.0015815045,
    "apr": 13.497743289635618,
    "fee": 0.0025,
    "version": "v4",
    "apr_change_24h": 0.9165336775688679,
    "apr_change_7d": -1.3729376664301873,
    "apr_change_30d": 8.477494316251637,
    "tvl_change_24h": -2.5354780782988895,
    "tvl_change_7d": -4.638235839138324,
    "tvl_change_30d": -6.829176938303792,
    "prediction_score": 58.998495526423746,
    "created_at": "2024-11-24T00:50:00.035612",
    "updated_at": "2025-04-26 00:50:00"
  },
  {
    "id": "XNDhFbuAm2aewPiGvirdWBmAso6SGym6RK8v4rr4HdzH",
    "name": "DOGWIFHAT/USDC",
    "dex": "Saber",
    "category": "Meme",
    "token1_symbol": "DOGWIFHAT",
    "token2_symbol": "USDC",
    "token1_address": "YwttziaUJnLsqaMazFJMpHvpKibBXsxpBQLPzL12dQxZ",
    "token2_address": "EPjFWdd5AufqSSqeM2qN1xzybapC8G4wEGGkZwyTDt1v",
    "liquidity": 3808042.333144018,
    "volume_24h": 457496.5039606223,
    "apr": 39.808329666780324,
    "fee": 0.003,
    "version": "v4",
    "apr_change_24h": -0.6802462156577467,
    "apr_change_7d": 3.7005548013133023,
    "apr_change_30d": -7.904508230429606,
    "tvl_change_24h": 2.0284264649411785,
    "tvl_change_7d": -0.035025717550151825,
    "tvl_change_30d": 10.58011173414161,
    "prediction_score": 95.0,
    "created_at": "2024-11-17T00:50:00.035612",
    "updated_at": "2025-04-26 00:50:00"
  },
  {
    "id": "KryjDVtoYMbmNqPXzUAdVq5JTh2kiNLi787Atj6jB3ak",
    "name": "ATLAS/USDC",
    "dex": "Orca",
    "category": "Gaming",
    "token1_symbol": "ATLAS",
    "token2_symbol": "USDC",
    "token1_address": "VNmxT8acXfWU7YTf3npaLiULwoCCwtPW7ypAcDrUnSb4",
    "token2_address": "EPjFWdd5AufqSSqeM2qN1xzybapC8G4wEGGkZwyTDt1v",
    "liquidity": 3849533.9838272883,
    "volume_24h": 505667.014769758,
    "apr": 25.12967403801268,
    "fee": 0.003,
    "version": "v4",
    "apr_change_24h": 1.407343321701608,
    "apr_change_7d": 0.14063523131909417,
    "apr_change_30d": -8.622557109986456,
    "tvl_change_24h": -2.462460938486707,
    "tvl_change_7d": 1.2417925858934655,
    "tvl_change_30d": -6.4260971079850755,
    "prediction_score": 86.7531160253418,
    "created_at": "2025-03-26T00:50:00.035612",
    "updated_at": "2025-04-26 00:50:00"
  },
  {
    "id": "kePp9hkyQrEkVyrYGhreVzzqi9Peogmg36vbnnenGfcp",
    "name": "FLOKI/USDC",
    "dex": "Orca",
    "category": "Meme",
    "token1_symbol": "FLOKI",
    "token2_symbol": "USDC",
    "token1_address": "W976X5vFF4dowbBDUkxwRHXT13MYzQLYbkrqFb2Des5z",
    "token2_address": "EPjFWdd5AufqSSqeM2qN1xzybapC8G4wEGGkZwyTDt1v",
    "liquidity": 8789559.28937741,
    "volume_24h": 2531067.948287521,
    "apr": 27.353564965702077,
    "fee": 0.003,
    "version": "v4",
    "apr_change_24h": 0.9991604936597964,
    "apr_change_7d": 2.105337160354641,
    "apr_change_30d": -2.2568289942398545,
    "tvl_change_24h": 2.448678302713878,
    "tvl_change_7d": 4.530869073088539,
    "tvl_change_30d": 6.9093752625181715,
    "prediction_score": 100,
    "created_at": "2024-11-27T00:50:00.035612",
    "updated_at": "2025-04-26 00:50:00"
  },
  {
    "id": "F8YtXQ5NVi1VXtmCj9ZbfjGjf3MuLpgi9KQRKQFyjSuG",
    "name": "LARIX/USDC",
    "dex": "Jupiter",
    "category": "Other",
    "token1_symbol": "LARIX",
    "token2_symbol": "USDC",
    "token1_address": "R2iNAQshjEoUMR51JUHCUTKoanRSWaSaADzTPcpFWQ9m",
    "token2_address": "EPjFWdd5AufqSSqeM2qN1xzybapC8G4wEGGkZwyTDt1v",
    "liquidity": 990550.0613571932,
    "volume_24h": 68993.71723532362,
    "apr": 18.44592671536292,
    "fee": 0.003,
    "version": "v4",
    "apr_change_24h": -0.5228128320418368,
    "apr_change_7d": 0.3642493706269665,
    "apr_change_30d": 0.08826084044831539,
    "tvl_change_24h": 0.9213313219406514,
    "tvl_change_7d": 0.9847849357434297,
    "tvl_change_30d": -14.594742122332791,
    "prediction_score": 82.29728447690862,
    "created_at": "2024-11-16T00:50:00.035612",
    "updated_at": "2025-04-26 00:50:00"
  },
  {
    "id": "odG1xf1wc7tqpN63MewtjcRh3mR22DrjShKNdGAGCk9d",
    "name": "RAY/SOL",
    "dex": "Raydium",
    "category": "DeFi",
    "token1_symbol": "RAY",
    "token2_symbol": "SOL",
    "token1_address": "4k3Dyjzvzp8eMZWUXbBCjEvwSkkk59S5iCNLY3QrkX6R",
    "token2_address": "So11111111111111111111111111111111111111112",
    "liquidity": 10208586.36849055,
    "volume_24h": 969537.2756927509,
    "apr": 21.88482712520795,
    "fee": 0.003,
    "version": "v4",
    "apr_change_24h": -0.726614377932147,
    "apr_change_7d": 4.554551740488767,
    "apr_change_30d": -6.947916060400541,
    "tvl_change_24h": 1.5011072548951443,
    "tvl_change_7d": 6.737904535743011,
    "tvl_change_30d": -5.472139477874503,
    "prediction_score": 94.58988475013864,
    "created_at": "2024-12-21T00:50:00.035612",
    "updated_at": "2025-04-26 00:50:00"
  },
  {
    "id": "QRM6NUhbD8tVFPujfC5JNStTSpqE7GqyUAuc8gz9Et6h",
    "name": "ETH/USDC",
    "dex": "Raydium",
    "category": "Major",
    "token1_symbol": "ETH",
    "token2_symbol": "USDC",
    "token1_address": "2FPyTwcZLUg1MDrwsyoP4D6s1tM7hAkHYRjkNb5w6Pxk",
    "token2_address": "EPjFWdd5AufqSSqeM2qN1xzybapC8G4wEGGkZwyTDt1v",
    "liquidity": 13922759.115713518,
    "volume_24h": 1755408.0677291218,
    "apr": 7.601577648683696,
    "fee": 0.0025,
    "version": "v4",
    "apr_change_24h": 0.6336487445075494,
    "apr_change_7d": -0.3075364781883376,
    "apr_change_30d": -9.381883880082153,
    "tvl_change_24h": -1.1093585599739804,
    "tvl_change_7d": -5.609684097024658,
    "tvl_change_30d": -6.175765735511618,
    "prediction_score": 55.0677184324558,
    "created_at": "2025-03-24T00:50:00.035612",
    "updated_at": "2025-04-26 00:50:00"
  },
  {
    "id": "zXK9BvAhgMayWLk5MkTEgviBkr36NrzQhkGktMBXDPME",
    "name": "SOL/USDT",
    "dex": "Meteora",
    "category": "Major",
    "token1_symbol": "SOL",
    "token2_symbol": "USDT",
    "token1_address": "So11111111111111111111111111111111111111112",
    "token2_address": "Es9vMFrzaCERmJfrF4H2FYD4KCoNkY11McCe8BenwNYB",
    "liquidity": 39752367.99460769,
    "volume_24h": 2638898.809430532,
    "apr": 9.737503203690729,
    "fee": 0.0025,
    "version": "v4",
    "apr_change_24h": -1.9604907899232433,
    "apr_change_7d": -2.8719958528990808,
    "apr_change_30d": -0.8372449329081455,
    "tvl_change_24h": 1.5966775935594928,
    "tvl_change_7d": -3.188901389369344,
    "tvl_change_30d": -7.164113364996734,
    "prediction_score": 56.49166880246049,
    "created_at": "2024-12-04T00:50:00.035612",
    "updated_at": "2025-04-26 00:50:00"
  },
  {
    "id": "jvx2zFg168EvWYcVotXrdrYuWP2KUggtBuDaCQKdGDUL",
    "name": "BTC/USDC",
    "dex": "Orca",
    "category": "Major",
    "token1_symbol": "BTC",
    "token2_symbol": "USDC",
    "token1_address": "9n4nbM75f5Ui33ZbPYXn59EwSgE8CGsHtAeTH5YFeJ9E",
    "token2_address": "EPjFWdd5AufqSSqeM2qN1xzybapC8G4wEGGkZwyTDt1v",
    "liquidity": 17743236.48936903,
    "volume_24h": 2132370.7329852805,
    "apr": 9.069073604616747,
    "fee": 0.0025,
    "version": "v4",
    "apr_change_24h": -1.6664957792937272,
    "apr_change_7d": 1.2348509090598023,
    "apr_change_30d": 0.1600612121644751,
    "tvl_change_24h": -2.798298919179132,
    "tvl_change_7d": -5.7528069708267315,
    "tvl_change_30d": -2.116445072308311,
    "prediction_score": 66.0460490697445,
    "created_at": "2025-02-16T00:50:00.035612",
    "updated_at": "2025-04-26 00:50:00"
  },
  {
    "id": "SBzbXsnDsnEQnkpZg3YicrERAhgXPEyqQ98tNGhjwhaN",
    "name": "BONK/USDC",
    "dex": "Raydium",
    "category": "Meme",
    "token1_symbol": "BONK",
    "token2_symbol": "USDC",
    "token1_address": "DezXAZ8z7PnrnRJjz3wXBoRgixCa6xjnB7YaB1pPB263",
    "token2_address": "EPjFWdd5AufqSSqeM2qN1xzybapC8G4wEGGkZwyTDt1v",
    "liquidity": 1746234.6171238308,
    "volume_24h": 299707.7943366452,
    "apr": 25.293845866307606,
    "fee": 0.003,
    "version": "v4",
    "apr_change_24h": 1.9375533414789654,
    "apr_change_7d": -2.021930053649333,
    "apr_change_30d": -6.1669107731772055,
    "tvl_change_24h": 1.0962929788211726,
    "tvl_change_7d": -4.151368975651224,
    "tvl_change_30d": -0.11930463937473057,
    "prediction_score": 81.86256391087174,
    "created_at": "2025-03-06T00:50:00.035612",
    "updated_at": "2025-04-26 00:50:00"
  },
  {
    "id": "DrNrcUroVdA17X5t3nwF67nSQT6hMJDn5JTkHdZXn9FA",
    "name": "BTC/USDC",
    "dex": "Raydium",
    "category": "Major",
    "token1_symbol": "BTC",
    "token2_symbol": "USDC",
    "token1_address": "9n4nbM75f5Ui33ZbPYXn59EwSgE8CGsHtAeTH5YFeJ9E",
    "token2_address": "EPjFWdd5AufqSSqeM2qN1xzybapC8G4wEGGkZwyTDt1v",
    "liquidity": 26381128.410727322,
    "volume_24h": 2086340.0210442634,
    "apr": 11.380013113816032,
    "fee": 0.0025,
    "version": "v4",
    "apr_change_24h": -1.8157641269392801,
    "apr_change_7d": 3.825027445785917,
    "apr_change_30d": 2.889977838189491,
    "tvl_change_24h": 0.5623323602090062,
    "tvl_change_7d": 6.183060898939539,
    "tvl_change_30d": -10.983581591991864,
    "prediction_score": 77.58667540921068,
    "created_at": "2025-02-21T00:50:00.035612",
    "updated_at": "2025-04-26 00:50:00"
  },
  {
    "id": "RrCTZrhCv37Yue3QX49jyur49gGUz6oDEjpuSceaw6ht",
    "name": "JUP/USDC",
    "dex": "Raydium",
    "category": "DeFi",
    "token1_symbol": "JUP",
    "token2_symbol": "USDC",
    "token1_address": "JUPyiwrYJFskUPiHa7hkeR8VUtAeFoSYbKedZJB7q2X",
    "token2_address": "EPjFWdd5AufqSSqeM2qN1xzybapC8G4wEGGkZwyTDt1v",
    "liquidity": 6299179.119122087,
    "volume_24h": 1130565.4900397288,
    "apr": 21.46671770867232,
    "fee": 0.003,
    "version": "v4",
    "apr_change_24h": 1.0952711387361616,
    "apr_change_7d": 2.693922686128581,
    "apr_change_30d": -7.309860724383781,
    "tvl_change_24h": 2.6938654539750377,
    "tvl_change_7d": -2.2218369333777446,
    "tvl_change_30d": -12.582598899287792,
    "prediction_score": 84.31114513911488,
    "created_at": "2025-02-11T00:50:00.035612",
    "updated_at": "2025-04-26 00:50:00"
  },
  {
    "id": "zdBmJWX6rToRR58HsWHWbgR91m4d6zGV7exZygbACifr",
    "name": "SOL/ETH",
    "dex": "Orca",
    "category": "Major",
    "token1_symbol": "SOL",
    "token2_symbol": "ETH",
    "token1_address": "So11111111111111111111111111111111111111112",
    "token2_address": "2FPyTwcZLUg1MDrwsyoP4D6s1tM7hAkHYRjkNb5w6Pxk",
    "liquidity": 28182809.94127435,
    "volume_24h": 2572864.4892651048,
    "apr": 14.284440277108134,
    "fee": 0.0025,
    "version": "v4",
    "apr_change_24h": 0.48284292263401163,
    "apr_change_7d": 3.9729718919588635,
    "apr_change_30d": 6.202241796288504,
    "tvl_change_24h": -2.5515209378442103,
    "tvl_change_7d": 4.483878302619338,
    "tvl_change_30d": -7.089393670990578,
    "prediction_score": 79.52296018473876,
    "created_at": "2024-12-23T00:50:00.035612",
    "updated_at": "2025-04-26 00:50:00"
  },
  {
    "id": "cKuS7yxRxQQ2nkTCeiK2t7WftS9NBnqypDU4DbSNrKAn",
    "name": "RAY/USDC",
    "dex": "Orca",
    "category": "DeFi",
    "token1_symbol": "RAY",
    "token2_symbol": "USDC",
    "token1_address": "4k3Dyjzvzp8eMZWUXbBCjEvwSkkk59S5iCNLY3QrkX6R",
    "token2_address": "EPjFWdd5AufqSSqeM2qN1xzybapC8G4wEGGkZwyTDt1v",
    "liquidity": 12930467.16477968,
    "volume_24h": 1626251.750480767,
    "apr": 20.705310773482395,
    "fee": 0.003,
    "version": "v4",
    "apr_change_24h": -1.2241438020838658,
    "apr_change_7d": -1.739967783842702,
    "apr_change_30d": -5.479875807898065,
    "tvl_change_24h": 1.3113732429554954,
    "tvl_change_7d": -2.5072757428450174,
    "tvl_change_30d": 4.979939329106426,
    "prediction_score": 73.80354051565493,
    "created_at": "2025-01-12T00:50:00.035612",
    "updated_at": "2025-04-26 00:50:00"
  }
]